odoo10_addon_web_advanced_search_wildcard-10.0.1.0.0-py2.7-nspkg.pth
odoo/addons/web_advanced_search_wildcard/README.rst
odoo/addons/web_advanced_search_wildcard/__init__.py
odoo/addons/web_advanced_search_wildcard/__manifest__.py
odoo/addons/web_advanced_search_wildcard/i18n/de.po
odoo/addons/web_advanced_search_wildcard/i18n/es.po
odoo/addons/web_advanced_search_wildcard/i18n/fi.po
odoo/addons/web_advanced_search_wildcard/i18n/fr.po
odoo/addons/web_advanced_search_wildcard/i18n/it.po
odoo/addons/web_advanced_search_wildcard/i18n/pt_BR.po
odoo/addons/web_advanced_search_wildcard/i18n/sl.po
odoo/addons/web_advanced_search_wildcard/i18n/tr.po
odoo/addons/web_advanced_search_wildcard/static/description/icon.png
odoo/addons/web_advanced_search_wildcard/static/description/screenshot.png
odoo/addons/web_advanced_search_wildcard/static/src/js/search.js
odoo/addons/web_advanced_search_wildcard/views/template.xml
odoo10_addon_web_advanced_search_wildcard-10.0.1.0.0.dist-info/DESCRIPTION.rst
odoo10_addon_web_advanced_search_wildcard-10.0.1.0.0.dist-info/METADATA
odoo10_addon_web_advanced_search_wildcard-10.0.1.0.0.dist-info/RECORD
odoo10_addon_web_advanced_search_wildcard-10.0.1.0.0.dist-info/WHEEL
odoo10_addon_web_advanced_search_wildcard-10.0.1.0.0.dist-info/metadata.json
odoo10_addon_web_advanced_search_wildcard-10.0.1.0.0.dist-info/namespace_packages.txt
odoo10_addon_web_advanced_search_wildcard-10.0.1.0.0.dist-info/top_level.txt
